README.rst
setup.cfg
setup.py
genomics/__init__.py
genomics/config.py
genomics/db/__init__.py
genomics/organism/__init__.py
genomics/parallel/__init__.py
genomics/parallel/executor.py
genomics/phylo/__init__.py
genomics/phylo/newick/__init__.py
genomics/phylo/newick/convert.py
genomics/plot/__init__.py
genomics/popgen/__init__.py
genomics/popgen/admix/__init__.py
genomics/popgen/admix/plot.py
genomics/popgen/genepop/__init__.py
genomics/popgen/genepop/convert.py
genomics/popgen/genepop/parser.py
genomics/popgen/ne2/__init__.py
genomics/popgen/ne2/controller.py
genomics/popgen/pca/__init__.py
genomics/popgen/pca/plot.py
genomics/popgen/pca/smart.py
genomics/popgen/plink/__init__.py
genomics/popgen/plink/convert.py
genomics/popgen/plink/parser.py
genomics/popgen/plot/__init__.py
genomics/popgen/stats/__init__.py
genomics/popgen/stats/dxy.py
genomics/popgen/stats/ld.py
pygenomics.egg-info/PKG-INFO
pygenomics.egg-info/SOURCES.txt
pygenomics.egg-info/dependency_links.txt
pygenomics.egg-info/requires.txt
pygenomics.egg-info/top_level.txt