Metadata-Version: 1.1
Name: pygenomics
Version: 0.1.5
Summary: A modern genomics library
Home-page: http://github.com/tiagoantao/pygenomics
Author: Tiago Antao
Author-email: tra@popgen.net
License: AGPLv3
Keywords: genomics genetics population-genetics population-genomics
Platform: UNKNOWN
Classifier: Development Status :: 3 - Alpha
Classifier: Programming Language :: Python :: 2.7
Classifier: Programming Language :: Python :: 3.4
Classifier: Topic :: Scientific/Engineering :: Bio-Informatics
Classifier: License :: OSI Approved :: GNU Affero General Public License v3
Classifier: Operating System :: POSIX :: Linux
Classifier: Intended Audience :: Developers
Classifier: Intended Audience :: Science/Research
